{
  "logs": [
    {
      "id": 2,
      "message": "Issue on server 1122",
      "attention": true,
      "tech": "Sam Wills",
      "date": "2019-10-27T15:13:27.410Z"
    },
    {
      "id": 3,
      "message": "test",
      "attention": false,
      "tech": "John Doe",
      "date": "2019-10-27T15:13:49.487Z"
    },
    {
      "id": 4,
      "message": "Log 3",
      "attention": true,
      "tech": "Sara Wilson",
      "date": "2019-10-27T15:14:03.426Z"
    },
    {
      "id": 5,
      "message": "Upgrade RAM  on SERVER 002",
      "attention": false,
      "tech": "John Doe",
      "date": "2019-10-27T15:14:09.355Z"
    }
  ],
  "techs": [
    {
      "id": 1,
      "firstname": "John",
      "lastname": "Doe"
    },
    {
      "firstname": "Sam",
      "lastname": "Wills",
      "id": 2
    },
    {
      "id": 3,
      "firstname": "Sara",
      "lastname": "Wilson"
    }
  ]
}